{
    "name": "Dominvm Red Light",
    "type": "light",
    "colors": {
        "focusBorder": "#C62828",
        "foreground": "#3D1515",
        "widget.shadow": "#CCB8B8",
        "selection.background": "#C6282840",
        "errorForeground": "#B71C1C",
        "button.background": "#C62828",
        "button.foreground": "#FFF5F5",
        "button.hoverBackground": "#B71C1C",
        "dropdown.background": "#FFF5F5",
        "dropdown.border": "#DDC8C8",
        "dropdown.foreground": "#3D1515",
        "input.background": "#FFF5F5",
        "input.border": "#DDC8C8",
        "input.foreground": "#3D1515",
        "input.placeholderForeground": "#999999",
        "scrollbar.shadow": "#CCB8B8",
        "scrollbarSlider.activeBackground": "#C6282880",
        "scrollbarSlider.background": "#CCB8B880",
        "scrollbarSlider.hoverBackground": "#DDC8C880",
        "badge.background": "#C62828",
        "badge.foreground": "#FFF5F5",
        "progressBar.background": "#C62828",
        "list.activeSelectionBackground": "#F0E0E0",
        "list.activeSelectionForeground": "#3D1515",
        "list.dropBackground": "#DDC8C8",
        "list.focusBackground": "#F0E0E0",
        "list.focusForeground": "#3D1515",
        "list.highlightForeground": "#C62828",
        "list.hoverBackground": "#F0E0E0",
        "list.hoverForeground": "#3D1515",
        "list.inactiveSelectionBackground": "#F0E0E0",
        "list.inactiveSelectionForeground": "#3D1515",
        "list.deemphasizedForeground": "#8B4444",
        "list.errorForeground": "#B71C1C",
        "list.warningForeground": "#E65100",
        "tree.indentGuidesStroke": "#CCB8B8",
        "tree.tableColumnsBorder": "#DDC8C8",
        "activityBar.background": "#DDC8C8",
        "activityBar.dropBorder": "#C62828",
        "activityBar.foreground": "#3D1515",
        "activityBar.inactiveForeground": "#999999",
        "activityBarBadge.background": "#C62828",
        "activityBarBadge.foreground": "#FFF5F5",
        "sideBar.background": "#F0E0E0",
        "sideBar.foreground": "#3D1515",
        "sideBarSectionHeader.background": "#DDC8C8",
        "sideBarSectionHeader.foreground": "#3D1515",
        "sideBarTitle.foreground": "#3D1515",
        "editorGroup.border": "#DDC8C8",
        "editorGroup.dropBackground": "#F0E0E080",
        "editorGroupHeader.noTabsBackground": "#FFF5F5",
        "editorGroupHeader.tabsBackground": "#F0E0E0",
        "tab.activeBackground": "#FFF5F5",
        "tab.activeForeground": "#3D1515",
        "tab.border": "#DDC8C8",
        "tab.activeBorder": "#C62828",
        "tab.inactiveBackground": "#F0E0E0",
        "tab.inactiveForeground": "#5C5C5C",
        "tab.unfocusedActiveBackground": "#FFF5F5",
        "tab.unfocusedActiveForeground": "#3D1515",
        "tab.unfocusedInactiveBackground": "#F0E0E0",
        "tab.unfocusedInactiveForeground": "#5C5C5C",
        "editor.background": "#FFF5F5",
        "editor.foreground": "#3D1515",
        "editorLineNumber.activeForeground": "#C62828",
        "editorLineNumber.foreground": "#808080",
        "editorCursor.foreground": "#B71C1C",
        "editor.selectionBackground": "#C6282840",
        "editor.inactiveSelectionBackground": "#DDC8C880",
        "editor.selectionHighlightBackground": "#F0E0E080",
        "editor.wordHighlightBackground": "#F0E0E080",
        "editor.wordHighlightStrongBackground": "#DDC8C880",
        "editor.findMatchBackground": "#C6282840",
        "editor.findMatchHighlightBackground": "#CCB8B880",
        "editor.hoverHighlightBackground": "#F0E0E080",
        "editor.lineHighlightBackground": "#F0E0E0",
        "editor.lineHighlightBorder": "#DDC8C8",
        "editorLink.activeForeground": "#C62828",
        "editorWhitespace.foreground": "#CCB8B8",
        "editorIndentGuide.background1": "#DDC8C8",
        "editorIndentGuide.activeBackground1": "#CCB8B8",
        "editorRuler.foreground": "#DDC8C8",
        "editorCodeLens.foreground": "#808080",
        "editorBracketMatch.background": "#DDC8C8",
        "editorBracketMatch.border": "#CCB8B8",
        "editorError.foreground": "#B71C1C",
        "editorWarning.foreground": "#E65100",
        "editorInfo.foreground": "#336666",
        "editorGutter.background": "#FFF5F5",
        "editorGutter.modifiedBackground": "#4FC3F7",
        "editorGutter.addedBackground": "#66BB6A",
        "editorGutter.deletedBackground": "#C62828",
        "diffEditor.insertedTextBackground": "#66BB6A40",
        "diffEditor.removedTextBackground": "#C6282840",
        "editorWidget.background": "#FFF5F5",
        "editorWidget.border": "#DDC8C8",
        "editorSuggestWidget.background": "#FFF5F5",
        "editorSuggestWidget.border": "#DDC8C8",
        "editorSuggestWidget.foreground": "#3D1515",
        "editorSuggestWidget.highlightForeground": "#C62828",
        "editorSuggestWidget.selectedBackground": "#F0E0E0",
        "editorHoverWidget.background": "#FFF5F5",
        "editorHoverWidget.border": "#DDC8C8",
        "peekView.border": "#C62828",
        "peekViewEditor.background": "#F0E0E0",
        "peekViewEditorGutter.background": "#F0E0E0",
        "peekViewEditor.matchHighlightBackground": "#C6282840",
        "peekViewResult.background": "#DDC8C8",
        "peekViewResult.fileForeground": "#3D1515",
        "peekViewResult.lineForeground": "#3D1515",
        "peekViewResult.matchHighlightBackground": "#C6282840",
        "peekViewResult.selectionBackground": "#CCB8B8",
        "peekViewResult.selectionForeground": "#3D1515",
        "peekViewTitle.background": "#DDC8C8",
        "peekViewTitleDescription.foreground": "#5C5C5C",
        "peekViewTitleLabel.foreground": "#3D1515",
        "panel.background": "#FFF5F5",
        "panel.border": "#CCB8B8",
        "panelTitle.activeBorder": "#C62828",
        "panelTitle.activeForeground": "#3D1515",
        "panelTitle.inactiveForeground": "#5C5C5C",
        "statusBar.background": "#DDC8C8",
        "statusBar.debuggingBackground": "#C62828",
        "statusBar.debuggingForeground": "#FFF5F5",
        "statusBar.noFolderBackground": "#DDC8C8",
        "statusBar.noFolderForeground": "#3D1515",
        "statusBar.foreground": "#3D1515",
        "statusBarItem.activeBackground": "#CCB8B8",
        "statusBarItem.hoverBackground": "#CCB8B8",
        "statusBarItem.prominentBackground": "#DDC8C8",
        "statusBarItem.prominentHoverBackground": "#CCB8B8",
        "titleBar.activeBackground": "#CCB8B8",
        "titleBar.activeForeground": "#3D1515",
        "titleBar.inactiveBackground": "#F0E0E0",
        "titleBar.inactiveForeground": "#5C5C5C",
        "welcomePage.background": "#FFF5F5",
        "welcomePage.tileBackground": "#F0E0E0",
        "welcomePage.tileHoverBackground": "#DDC8C8",
        "welcomePage.tileBorder": "#DDC8C8",
        "welcomePage.progress.background": "#DDC8C8",
        "welcomePage.progress.foreground": "#C62828",
        "walkthrough.stepTitle.foreground": "#3D1515",
        "textLink.foreground": "#C62828",
        "textLink.activeForeground": "#B71C1C",
        "textBlockQuote.background": "#F0E0E0",
        "textBlockQuote.border": "#C62828",
        "textCodeBlock.background": "#F0E0E0",
        "textPreformat.foreground": "#B71C1C",
        "textSeparator.foreground": "#DDC8C8",
        "icon.foreground": "#B71C1C",
        "keybindingLabel.background": "#F0E0E0",
        "keybindingLabel.foreground": "#3D1515",
        "keybindingLabel.border": "#DDC8C8",
        "keybindingLabel.bottomBorder": "#CCB8B8"
    },
    "tokenColors": [
        {
            "name": "Comment",
            "scope": [
                "comment",
                "punctuation.definition.comment",
                "string.comment"
            ],
            "settings": {
                "foreground": "#808080",
                "fontStyle": "italic"
            }
        },
        {
            "name": "Keywords & Storage",
            "scope": [
                "keyword",
                "storage",
                "storage.type",
                "entity.name.tag",
                "keyword.control",
                "keyword.operator.new",
                "keyword.operator.expression",
                "keyword.operator.logical"
            ],
            "settings": {
                "foreground": "#B71C1C"
            }
        },
        {
            "name": "Strings",
            "scope": [
                "string",
                "punctuation.definition.string",
                "string.quoted",
                "markup.inline.raw"
            ],
            "settings": {
                "foreground": "#4D734D"
            }
        },
        {
            "name": "Headers & Highlights",
            "scope": [
                "markup.heading",
                "markup.heading.setext",
                "markup.heading.markdown",
                "punctuation.definition.heading",
                "entity.name.section"
            ],
            "settings": {
                "foreground": "#C62828",
                "fontStyle": "bold"
            }
        },
        {
            "name": "Functions & Methods",
            "scope": [
                "entity.name.function",
                "support.function",
                "meta.function-call",
                "entity.name.method",
                "support.function.method",
                "meta.method-call",
                "entity.name.function.decorator",
                "meta.decorator"
            ],
            "settings": {
                "foreground": "#336666"
            }
        },
        {
            "name": "Classes & Types",
            "scope": [
                "entity.name.class",
                "entity.name.type",
                "support.class",
                "support.type",
                "entity.other.inherited-class",
                "meta.class",
                "meta.type"
            ],
            "settings": {
                "foreground": "#7A527A",
                "fontStyle": "bold"
            }
        },
        {
            "name": "Variables & Parameters",
            "scope": [
                "variable",
                "support.variable",
                "punctuation.definition.variable",
                "variable.parameter",
                "variable.other",
                "variable.language",
                "meta.parameter-type"
            ],
            "settings": {
                "foreground": "#5C5C5C"
            }
        },
        {
            "name": "Numbers & Booleans",
            "scope": [
                "constant.numeric",
                "constant.language",
                "constant.character",
                "constant.other",
                "support.constant"
            ],
            "settings": {
                "foreground": "#8B5E5E"
            }
        },
        {
            "name": "Object Properties & Keys",
            "scope": [
                "meta.object-literal.key",
                "support.type.property-name",
                "variable.object.property",
                "entity.name.label",
                "string.unquoted.label"
            ],
            "settings": {
                "foreground": "#7A4D4D"
            }
        },
        {
            "name": "Operators & Punctuation",
            "scope": [
                "keyword.operator",
                "punctuation.separator",
                "punctuation.terminator",
                "punctuation.section",
                "punctuation.definition",
                "meta.brace"
            ],
            "settings": {
                "foreground": "#6B4747"
            }
        },
        {
            "name": "Markup Formatting",
            "scope": [
                "markup.bold",
                "markup.italic",
                "markup.strikethrough",
                "markup.underline",
                "markup.quote",
                "markup.list"
            ],
            "settings": {
                "foreground": "#804040"
            }
        },
        {
            "name": "Regex & Escapes",
            "scope": [
                "string.regexp",
                "constant.character.escape",
                "constant.character.escape.backslash"
            ],
            "settings": {
                "foreground": "#7A4D4D"
            }
        }
    ]
}